LICENSE
README.md
setup.py
Corpus/AbstractCorpus.py
Corpus/Corpus.py
Corpus/CorpusStream.py
Corpus/EnglishSplitter.py
Corpus/FileDescription.py
Corpus/LanguageChecker.py
Corpus/Paragraph.py
Corpus/Sentence.py
Corpus/SentenceSplitter.py
Corpus/TurkishChecker.py
Corpus/TurkishSplitter.py
Corpus/WordFormat.py
Corpus/__init__.py
NlpToolkit_Corpus.egg-info/PKG-INFO
NlpToolkit_Corpus.egg-info/SOURCES.txt
NlpToolkit_Corpus.egg-info/dependency_links.txt
NlpToolkit_Corpus.egg-info/requires.txt
NlpToolkit_Corpus.egg-info/top_level.txt