Metadata-Version: 2.1
Name: NlpToolkit-Corpus
Version: 1.0.24
Summary: Corpus library
Home-page: https://github.com/StarlangSoftware/Corpus-Py
Author: olcaytaner
Author-email: olcay.yildiz@ozyegin.edu.tr
License: UNKNOWN
Platform: UNKNOWN
